frogfast/update.py
frogfast/c/gcc.py
frogfast/c/main.py
frogfast/cpp/gpp.py
frogfast/cpp/main.py
frogfast/pythonc/__init__.py
frogfast/pythonc/initer.py
frogfast/pythonc/main.py
frogfast/pythonc/nuitkac.py
frogfast/utils/apply_icon.py
frogfast-0.1.2.dist-info/METADATA
frogfast-0.1.2.dist-info/WHEEL
frogfast-0.1.2.dist-info/entry_points.txt
frogfast-0.1.2.dist-info/top_level.txt
frogfast-0.1.2.dist-info/RECORD
