Metadata-Version: 2.4
Name: frogfast
Version: 0.1.2
Summary: Fast build tool for Python projects
Author: Pratyush
License: MIT
Requires-Python: >=3.9
Requires-Dist: Pillow
Requires-Dist: nuitka
